storycraft/app.py
storycraft/blocks.py
storycraft/imgen.py
storycraft/main.py
storycraft/novel.py
storycraft/project.py
storycraft/settings.py
storycraft/writer.py
storycraft/prompts/chapter-content.md
storycraft/prompts/extended-outline.md
storycraft/prompts/instructions.md
storycraft/prompts/outline-with-title.md
storycraft/prompts/outline.md
storycraft/prompts/title.md
storycraft-0.0.1.dist-info/METADATA
storycraft-0.0.1.dist-info/WHEEL
storycraft-0.0.1.dist-info/entry_points.txt
storycraft-0.0.1.dist-info/RECORD
