Metadata-Version: 2.4
Name: storycraft
Version: 0.0.1
Summary: ...
Requires-Python: >=3.13
Requires-Dist: agentia
Requires-Dist: fal-client>=0.5.9
Requires-Dist: jinja2>=3.1.6
Requires-Dist: pydantic>=2.11.3
Requires-Dist: python-frontmatter>=1.1.0
Requires-Dist: python-slugify[unidecode]>=8.0.4
Requires-Dist: pyyaml>=6.0.2
Requires-Dist: shortuuid>=1.0.13
Requires-Dist: streamlit>=1.44.1
Requires-Dist: typer>=0.12.5
